circuitsapi/__init__.py
circuitsapi/client.py
circuitsapi/exceptions.py
circuitsapi/helpers.py
circuitsapi/request.py
circuitsapi-0.0.4.dist-info/LICENSE
circuitsapi-0.0.4.dist-info/METADATA
circuitsapi-0.0.4.dist-info/WHEEL
circuitsapi-0.0.4.dist-info/top_level.txt
circuitsapi-0.0.4.dist-info/RECORD
