Metadata-Version: 2.1
Name: circuitsapi
Version: 0.0.4
Summary: CircuitsAPI is a system to transmit data to Rec Room circuits.
Author: Jegarde
Project-URL: Homepage, https://github.com/Jegarde/CircuitsAPI
Project-URL: Bug Tracker, https://github.com/Jegarde/CircuitsAPI/issues
Classifier: Programming Language :: Python :: 3
Classifier: License :: OSI Approved :: MIT License
Classifier: Operating System :: OS Independent
Requires-Python: >=3.10
License-File: LICENSE
Requires-Dist: PyJWT ==2.7.0
Requires-Dist: python-dotenv ==1.0.0
Requires-Dist: aiohttp ==3.9.2
Requires-Dist: recnetpy ==0.2.71
Requires-Dist: python-dateutil ==2.8.2
Requires-Dist: recnetlogin ==0.1.1
